sihnpy/__init__.py
sihnpy/data/__init__.py
sihnpy/data/fingerprinting/__init__.py
sihnpy/data/fingerprinting/fp_simulated_id_list.csv
sihnpy/data/fingerprinting/matrices_simulated_mod1/mat_010a.txt
sihnpy/data/fingerprinting/matrices_simulated_mod1/mat_01a.txt
sihnpy/data/fingerprinting/matrices_simulated_mod1/mat_02a.txt
sihnpy/data/fingerprinting/matrices_simulated_mod1/mat_03a.txt
sihnpy/data/fingerprinting/matrices_simulated_mod1/mat_04a.txt
sihnpy/data/fingerprinting/matrices_simulated_mod1/mat_05a.txt
sihnpy/data/fingerprinting/matrices_simulated_mod1/mat_06a.txt
sihnpy/data/fingerprinting/matrices_simulated_mod1/mat_07a.txt
sihnpy/data/fingerprinting/matrices_simulated_mod1/mat_08a.txt
sihnpy/data/fingerprinting/matrices_simulated_mod1/mat_09a.txt
sihnpy/data/fingerprinting/matrices_simulated_mod2/mat_010a.txt
sihnpy/data/fingerprinting/matrices_simulated_mod2/mat_01a.txt
sihnpy/data/fingerprinting/matrices_simulated_mod2/mat_02a.txt
sihnpy/data/fingerprinting/matrices_simulated_mod2/mat_03a.txt
sihnpy/data/fingerprinting/matrices_simulated_mod2/mat_04a.txt
sihnpy/data/fingerprinting/matrices_simulated_mod2/mat_05a.txt
sihnpy/data/fingerprinting/matrices_simulated_mod2/mat_06a.txt
sihnpy/data/fingerprinting/matrices_simulated_mod2/mat_07a.txt
sihnpy/data/fingerprinting/matrices_simulated_mod2/mat_08a.txt
sihnpy/data/fingerprinting/matrices_simulated_mod2/mat_09a.txt
sihnpy/data/fingerprinting_tab/__init__.py
sihnpy/data/fingerprinting_tab/conp_fsv7_1_0_aseg.csv
sihnpy/data/fingerprinting_tab/conp_fsv7_1_0_thickness.csv
sihnpy/data/fingerprinting_tab/conp_fsv7_1_0_volume.csv
sihnpy/data/imbalance_mapping/__init__.py
sihnpy/data/imbalance_mapping/conp_fsv7_1_0_aseg.csv
sihnpy/data/imbalance_mapping/conp_fsv7_1_0_thickness.csv
sihnpy/data/imbalance_mapping/conp_fsv7_1_0_volume.csv
sihnpy/data/pad_conp_minimal/BL00/encoding/sub-1000173_ses-BL00_task-encoding_run-1.tsv
sihnpy/data/pad_conp_minimal/BL00/encoding/sub-1004359_ses-BL00_task-encoding_run-1.tsv
sihnpy-0.4.1.dist-info/LICENSE.md
sihnpy-0.4.1.dist-info/METADATA
sihnpy-0.4.1.dist-info/WHEEL
sihnpy-0.4.1.dist-info/RECORD
